mrirecon/__init__.py
mrirecon/kt_sense.py
mrirecon/sense.py
mrirecon/functional/__init__.py
mrirecon/functional/domain_conversion.py
mrirecon-0.0.2.dist-info/LICENSE
mrirecon-0.0.2.dist-info/METADATA
mrirecon-0.0.2.dist-info/WHEEL
mrirecon-0.0.2.dist-info/top_level.txt
mrirecon-0.0.2.dist-info/RECORD
