Metadata-Version: 2.1
Name: mrirecon
Version: 0.0.2
Summary: MRI reconstruction toolbox. PyTorch.
Home-page: https://github.com/denproc/mrirecon
Author: Denis Prokopenko
Author-email: d.prokopenko@outlook.com
Classifier: Programming Language :: Python :: 3
Classifier: License :: OSI Approved :: Apache Software License
Classifier: Operating System :: OS Independent
License-File: LICENSE
Requires-Dist: torch >=1.10
